{
  "entity.end_crystal.hit": {
    "subtitle": "sounds.frontiers.end_crystal_hit",
    "sounds": [
      "frontiers:end_crystal/end_crystal_hit_1",
      "frontiers:end_crystal/end_crystal_hit_2",
      "frontiers:end_crystal/end_crystal_hit_3"
    ]
  },
  "entity.end_crystal.wail": {
    "subtitle": "sounds.frontiers.end_crystal_wail",
    "sounds": [
      "frontiers:end_crystal/end_crystal_wail"
    ]
  },
  "entity.end_crystal.explode": {
    "subtitle": "sounds.frontiers.end_crystal_explode",
    "sounds": [
      "frontiers:end_crystal/end_crystal_explode"
    ]
  },
  "entity.player.spell_cast": {
    "subtitle": "sounds.frontiers.spell_cast",
    "sounds": [
      "minecraft:mob/evocation_illager/cast1",
      "minecraft:mob/evocation_illager/cast2"
    ]
  },
  "entity.player.spell_cast_fangs": {
    "subtitle": "sounds.frontiers.spell_cast_fangs",
    "sounds": [
      "minecraft:mob/evocation_illager/prepare_attack1",
      "minecraft:mob/evocation_illager/prepare_attack2"
    ]
  },
  "entity.arrow.shoot_verdinite": {
    "subtitle": "sounds.frontiers.verdinite_bow",
    "sounds": [
      "frontiers:verdinite_bow/shoot"
    ]
  },
  "item.armor.equip_cobalt": {
    "subtitle": "sounds.frontiers.equip.cobalt",
    "sounds": [
      "frontiers:armor/cobalt/equip1",
      "frontiers:armor/cobalt/equip2",
      "frontiers:armor/cobalt/equip3",
      "frontiers:armor/cobalt/equip4"
    ]
  },
  "ui.toast.frontier_reached": {
    "sounds": [
      {
        "name": "frontiers:end_crystal/end_crystal_explode",
        "volume": 0.8
      }
    ]
  },
  "item.void_pearl.use": {
    "subtitle": "sounds.frontiers.void_pearl.use",
    "sounds": [
      "frontiers:void_pearl/use"
    ]
  },
  "block.skull.steve": {
    "subtitle": "sounds.frontiers.block.skull.steve",
    "sounds": [
      "frontiers:heads/steve_old"
    ]
  },
  "block.skull.artyrian": {
    "subtitle": "sounds.frontiers.block.skull.artyrian",
    "sounds": [
      "frontiers:heads/artyrian/artyrian_1",
      "frontiers:heads/artyrian/artyrian_2",
      "frontiers:heads/artyrian/artyrian_3",
      "frontiers:heads/artyrian/artyrian_4",
      "frontiers:heads/artyrian/artyrian_5",
      "frontiers:heads/artyrian/artyrian_6"
    ]
  },
  "block.skull.xenona": {
    "subtitle": "sounds.frontiers.block.skull.xenona",
    "sounds": [
      "frontiers:heads/xenona/xenona_1",
      "frontiers:heads/xenona/xenona_2",
      "frontiers:heads/xenona/xenona_3",
      "frontiers:heads/xenona/xenona_4",
      "frontiers:heads/xenona/xenona_5",
      {
        "name": "mob/sheep/say1",
        "pitch": 1.5
      },
      {
        "name": "mob/sheep/say2",
        "pitch": 1.5
      },
      {
        "name": "mob/sheep/say3",
        "pitch": 1.5
      }
    ]
  }
}